acouchbase/__init__.py
acouchbase/analytics.py
acouchbase/binary_collection.py
acouchbase/bucket.py
acouchbase/cluster.py
acouchbase/collection.py
acouchbase/datastructures.py
acouchbase/kv_range_scan.py
acouchbase/n1ql.py
acouchbase/scope.py
acouchbase/search.py
acouchbase/views.py
acouchbase/logic/__init__.py
acouchbase/logic/wrappers.py
acouchbase/management/__init__.py
acouchbase/management/analytics.py
acouchbase/management/buckets.py
acouchbase/management/collections.py
acouchbase/management/eventing.py
acouchbase/management/queries.py
acouchbase/management/search.py
acouchbase/management/users.py
acouchbase/management/views.py
acouchbase/management/logic/__init__.py
acouchbase/management/logic/wrappers.py
acouchbase/transactions/__init__.py
acouchbase/transactions/transactions.py
couchbase/__init__.py
couchbase/_utils.py
couchbase/_version.py
couchbase/analytics.py
couchbase/auth.py
couchbase/binary_collection.py
couchbase/bucket.py
couchbase/cluster.py
couchbase/collection.py
couchbase/constants.py
couchbase/datastructures.py
couchbase/diagnostics.py
couchbase/durability.py
couchbase/exceptions.py
couchbase/kv_range_scan.py
couchbase/metrics.py
couchbase/mutation_state.py
couchbase/n1ql.py
couchbase/options.py
couchbase/otel_tracer.py
couchbase/pycbc_core.so
couchbase/replica_reads.py
couchbase/result.py
couchbase/scope.py
couchbase/search.py
couchbase/serializer.py
couchbase/subdocument.py
couchbase/tracing.py
couchbase/transcoder.py
couchbase/vector_search.py
couchbase/views.py
couchbase/encryption/__init__.py
couchbase/encryption/crypto_manager.py
couchbase/encryption/decrypter.py
couchbase/encryption/encrypter.py
couchbase/encryption/encryption_result.py
couchbase/encryption/key.py
couchbase/encryption/keyring.py
couchbase/logic/__init__.py
couchbase/logic/analytics.py
couchbase/logic/bucket.py
couchbase/logic/cluster.py
couchbase/logic/collection.py
couchbase/logic/kv_range_scan.py
couchbase/logic/n1ql.py
couchbase/logic/options.py
couchbase-4.5.0.dist-info/licenses/LICENSE
couchbase-4.5.0.dist-info/METADATA
couchbase-4.5.0.dist-info/WHEEL
couchbase-4.5.0.dist-info/top_level.txt
couchbase-4.5.0.dist-info/RECORD
